saltext/tsl/__init__.py
saltext/tsl/loader.py
saltext/tsl/modules/__init__.py
saltext/tsl/modules/tsl_mod.py
saltext.tsl-1.4.0.dist-info/LICENSE
saltext.tsl-1.4.0.dist-info/METADATA
saltext.tsl-1.4.0.dist-info/WHEEL
saltext.tsl-1.4.0.dist-info/entry_points.txt
saltext.tsl-1.4.0.dist-info/top_level.txt
saltext.tsl-1.4.0.dist-info/RECORD
