Metadata-Version: 2.1
Name: saltext.tsl
Version: 1.4.0
Summary: TSL - The State Library Module
Author-email: TurtleTraction <info@turtletraction.com>
License: Apache License
Project-URL: Homepage, https://www.turtletraction.com/state-library
Project-URL: Bug Reports, https://gitlab.com/turtletraction-oss/saltext-tsl/-/issues
Project-URL: Source, https://gitlab.com/turtletraction-oss/saltext-tsl
Keywords: salt-extension
Classifier: Programming Language :: Python
Classifier: Programming Language :: Cython
Classifier: Programming Language :: Python :: 3
Classifier: Programming Language :: Python :: 3 :: Only
Classifier: Programming Language :: Python :: 3.5
Classifier: Programming Language :: Python :: 3.6
Classifier: Programming Language :: Python :: 3.7
Classifier: Programming Language :: Python :: 3.8
Classifier: Programming Language :: Python :: 3.9
Classifier: Programming Language :: Python :: 3.10
Classifier: Development Status :: 4 - Beta
Classifier: Intended Audience :: Developers
Classifier: License :: OSI Approved :: Apache Software License
Requires-Python: >=3.5
License-File: LICENSE
Requires-Dist: salt >=3004
Provides-Extra: dev
Requires-Dist: nox ==2023.04.22 ; extra == 'dev'
Requires-Dist: pre-commit ==3.4.0 ; extra == 'dev'
Requires-Dist: pylint ; extra == 'dev'
Requires-Dist: SaltPyLint ; extra == 'dev'
Requires-Dist: twine ; extra == 'dev'
Requires-Dist: build ; extra == 'dev'
Provides-Extra: docs
Requires-Dist: sphinx ; extra == 'docs'
Requires-Dist: sphinx-pyproject ; extra == 'docs'
Requires-Dist: furo ; extra == 'docs'
Requires-Dist: sphinx-copybutton ; extra == 'docs'
Requires-Dist: sphinx-prompt ; extra == 'docs'
Requires-Dist: sphinxcontrib-spelling ; extra == 'docs'
Requires-Dist: importlib-metadata ; (python_version < "3.8") and extra == 'docs'
Provides-Extra: docsauto
Requires-Dist: sphinx-autobuild ; extra == 'docsauto'
Provides-Extra: tests
Requires-Dist: pytest ==7.4.3 ; extra == 'tests'
Requires-Dist: pytest-salt-factories ==1.0.1 ; extra == 'tests'
